shimexpy/__init__.py
shimexpy/core/__init__.py
shimexpy/core/contrast.py
shimexpy/core/spatial_harmonics.py
shimexpy/core/unwrapping.py
shimexpy/data/__init__.py
shimexpy/data/loader.py
shimexpy/io/__init__.py
shimexpy/io/file_io.py
shimexpy/utils/__init__.py
shimexpy/utils/crop.py
shimexpy/utils/ffc.py
shimexpy/utils/parallelization.py
shimexpy/visualization/__init__.py
shimexpy/visualization/plot.py
shimexpy_core-0.1.0.dist-info/METADATA
shimexpy_core-0.1.0.dist-info/WHEEL
shimexpy_core-0.1.0.dist-info/top_level.txt
shimexpy_core-0.1.0.dist-info/RECORD
