Metadata-Version: 2.4
Name: shimexpy-core
Version: 0.1.0
Summary: An open-source Python package for spatial harmonics X-ray imaging.
Author: Jorge Luis Beltran Diaz
License: Apache-2.0
Classifier: Development Status :: 3 - Alpha
Classifier: Intended Audience :: Science/Research
Classifier: License :: OSI Approved :: Apache Software License
Classifier: Programming Language :: Python :: 3
Classifier: Programming Language :: Python :: 3.7
Classifier: Programming Language :: Python :: 3.8
Classifier: Programming Language :: Python :: 3.9
Classifier: Programming Language :: Python :: 3.10
Classifier: Programming Language :: Python :: 3.11
Classifier: Operating System :: POSIX :: Linux
Requires-Python: >=3.7
Requires-Dist: numpy
Requires-Dist: xarray
Requires-Dist: dask
Requires-Dist: matplotlib
Requires-Dist: scikit-image
Requires-Dist: tifffile
Requires-Dist: scipy
Provides-Extra: dev
Requires-Dist: pytest; extra == "dev"
Requires-Dist: setuptools; extra == "dev"
Requires-Dist: build; extra == "dev"
Requires-Dist: twine; extra == "dev"
Provides-Extra: cuda13x
Requires-Dist: cupy-cuda13x; extra == "cuda13x"
Provides-Extra: cuda12x
Requires-Dist: cupy-cuda12x; extra == "cuda12x"
Provides-Extra: cuda11x
Requires-Dist: cupy-cuda11x; extra == "cuda11x"
